linear_equations/__init__.py
linear_equations-0.0.7.dist-info/LICENSE.txt
linear_equations-0.0.7.dist-info/METADATA
linear_equations-0.0.7.dist-info/WHEEL
linear_equations-0.0.7.dist-info/top_level.txt
linear_equations-0.0.7.dist-info/RECORD
