Metadata-Version: 2.1
Name: linear-equations
Version: 0.0.7
Summary: provides Linear Equations in 2 variables as Python Objects
Home-page: https://github.com/divyajeettt/linear-equations
Author: Divyajeet Singh
Author-email: knightt1821@gmail.com
Classifier: Programming Language :: Python :: 3
Classifier: License :: OSI Approved :: MIT License
Classifier: Operating System :: OS Independent
License-File: LICENSE.txt
Requires-Dist: matplotlib
